  2           0 LOAD_CONST               0 (<code object foo at 0x10b2ac9d0, file "test.py", line 2>)
              2 LOAD_CONST               1 ('foo')
              4 MAKE_FUNCTION            0
              6 STORE_NAME               0 (foo)

  5           8 LOAD_CONST               2 (<code object bar at 0x10b2aca80, file "test.py", line 5>)
             10 LOAD_CONST               3 ('bar')
             12 MAKE_FUNCTION            0
             14 STORE_NAME               1 (bar)
             16 LOAD_CONST               4 (None)
             18 RETURN_VALUE

Disassembly of <code object foo at 0x10b2ac9d0, file "test.py", line 2>:
  3           0 LOAD_FAST                0 (x)
              2 LOAD_CONST               1 (2)
              4 BINARY_POWER
              6 RETURN_VALUE

Disassembly of <code object bar at 0x10b2aca80, file "test.py", line 5>:
  6           0 LOAD_FAST                0 (x)
              2 LOAD_CONST               1 (2)
              4 BINARY_TRUE_DIVIDE
              6 STORE_FAST               1 (y)

  7           8 LOAD_FAST                1 (y)
             10 RETURN_VALUE
exitcode:-443625908
